murl/__init__.py
murl/cli.py
mcp_curl-0.2.2.dist-info/LICENSE
mcp_curl-0.2.2.dist-info/METADATA
mcp_curl-0.2.2.dist-info/WHEEL
mcp_curl-0.2.2.dist-info/entry_points.txt
mcp_curl-0.2.2.dist-info/top_level.txt
mcp_curl-0.2.2.dist-info/RECORD
