Metadata-Version: 2.2
Name: mcp-curl
Version: 0.2.2
Summary: A curl-like CLI tool for interacting with Model Context Protocol (MCP) servers
Author: turlockmike
License: MIT
Project-URL: Homepage, https://github.com/turlockmike/murl
Project-URL: Repository, https://github.com/turlockmike/murl
Project-URL: Issues, https://github.com/turlockmike/murl/issues
Classifier: Development Status :: 3 - Alpha
Classifier: Intended Audience :: Developers
Classifier: Programming Language :: Python :: 3
Classifier: Programming Language :: Python :: 3.10
Classifier: Programming Language :: Python :: 3.11
Classifier: Programming Language :: Python :: 3.12
Classifier: Programming Language :: Python :: 3.13
Classifier: Programming Language :: Python :: 3.14
Requires-Python: >=3.10
License-File: LICENSE
Requires-Dist: click>=8.0.0
Requires-Dist: mcp>=1.0.0
Requires-Dist: exceptiongroup>=1.0.0; python_version < "3.11"
Provides-Extra: dev
Requires-Dist: pytest>=7.0.0; extra == "dev"
Requires-Dist: pytest-cov>=4.0.0; extra == "dev"
Requires-Dist: requests>=2.31.0; extra == "dev"
